bengali_analyzer/__init__.py
bengali_analyzer/bengalianalyzer.py
bengali_analyzer/assets/banglaNonFiniteVerbs.csv
bengali_analyzer/assets/not_to_be_broken.txt
bengali_analyzer/assets/numerics.json
bengali_analyzer/assets/parent_verbs.csv
bengali_analyzer/assets/prefixes.csv
bengali_analyzer/assets/pronouns.csv
bengali_analyzer/assets/special_suffixes.csv
bengali_analyzer/assets/suffixes.csv
bengali_analyzer/assets/verbs.csv
bengali_analyzer/assets/wordListPoS.csv
bengali_analyzer/libs/__init__.py
bengali_analyzer/libs/composite_words.py
bengali_analyzer/libs/non_verbs.py
bengali_analyzer/libs/numerics.py
bengali_analyzer/libs/pronouns.py
bengali_analyzer/libs/special_entity.py
bengali_analyzer/libs/verbs.py
bengali_analyzer/normalizer/__init__.py
bengali_analyzer/normalizer/checksum.json
bengali_analyzer/normalizer/normalize_assets.py
bengali_analyzer/utilis/__init__.py
bengali_analyzer/utilis/utils.py
bengalianalyzer-0.0.109.dist-info/METADATA
bengalianalyzer-0.0.109.dist-info/WHEEL
bengalianalyzer-0.0.109.dist-info/top_level.txt
bengalianalyzer-0.0.109.dist-info/RECORD
