Metadata-Version: 2.1
Name: bengalianalyzer
Version: 0.0.109
Summary: A package for analyzing entities present in Bengali sentence
Home-page: https://github.com/BengaliAI/bengaliAnalyzer
Author: A. A. Noman Ansary
Author-email: showrav.ansary.bd@gmail.com
License: BSD 3-Clause New or Revised License
Project-URL: Bug Tracker, https://github.com/BengaliAI/bengaliAnalyzer/issues
Classifier: Development Status :: 2 - Pre-Alpha
Classifier: Programming Language :: Python :: 3
Classifier: License :: OSI Approved :: BSD License
Classifier: Operating System :: Unix
Requires-Python: >=3.7
Requires-Dist: pandas
Requires-Dist: indicparser
Requires-Dist: bnunicodenormalizer
Requires-Dist: tqdm
Requires-Dist: termcolor
